shipdan_model/__init__.py
shipdan_model/urls.py
shipdan_model/app_model/__init__.py
shipdan_model/app_model/accounts.py
shipdan_model/app_model/analysis.py
shipdan_model/app_model/apps.py
shipdan_model/app_model/constant.py
shipdan_model/app_model/core.py
shipdan_model/app_model/delivery.py
shipdan_model/app_model/diary.py
shipdan_model/app_model/diet.py
shipdan_model/app_model/diet_survey.py
shipdan_model/app_model/food.py
shipdan_model/app_model/food_payment.py
shipdan_model/app_model/health.py
shipdan_model/app_model/notification.py
shipdan_model/app_model/oms.py
shipdan_model/app_model/payment.py
shipdan_model/app_model/social_app.py
shipdan_model/app_model/survey.py
shipdan_model/app_model/migrations/0001_initial.py
shipdan_model/app_model/migrations/__init__.py
shipdan_model/settings/__init__.py
shipdan_model/settings/asgi.py
shipdan_model/settings/base.py
shipdan_model/settings/wsgi.py
shipdan_model/shipdan_apps/accounts_model/__init__.py
shipdan_model/shipdan_apps/accounts_model/apps.py
shipdan_model/shipdan_apps/accounts_model/models.py
shipdan_model/shipdan_apps/accounts_model/migrations/__init__.py
shipdan_model/shipdan_apps/analysis_model/__init__.py
shipdan_model/shipdan_apps/analysis_model/apps.py
shipdan_model/shipdan_apps/analysis_model/models.py
shipdan_model/shipdan_apps/analysis_model/migrations/__init__.py
shipdan_model/shipdan_apps/core_model/__init__.py
shipdan_model/shipdan_apps/core_model/apps.py
shipdan_model/shipdan_apps/core_model/models.py
shipdan_model/shipdan_apps/core_model/migrations/__init__.py
shipdan_model/shipdan_apps/delivery_model/__init__.py
shipdan_model/shipdan_apps/delivery_model/apps.py
shipdan_model/shipdan_apps/delivery_model/models.py
shipdan_model/shipdan_apps/delivery_model/migrations/__init__.py
shipdan_model/shipdan_apps/diary_model/__init__.py
shipdan_model/shipdan_apps/diary_model/admin.py
shipdan_model/shipdan_apps/diary_model/apps.py
shipdan_model/shipdan_apps/diary_model/models.py
shipdan_model-0.0.26.dist-info/LICENSE.rst
shipdan_model-0.0.26.dist-info/METADATA
shipdan_model-0.0.26.dist-info/WHEEL
shipdan_model-0.0.26.dist-info/top_level.txt
shipdan_model-0.0.26.dist-info/RECORD
