Metadata-Version: 2.1
Name: shipdan-model
Version: 0.0.26
Summary: app_model package for shipdan business written by Bunkerkids Tech
Home-page: https://github.com/bunkerkids/shipdan_model
Author: bunkerkids
Author-email: development@bunkerkids.net
Classifier: Programming Language :: Python :: 3.9
Classifier: Programming Language :: Python :: 3.10
Classifier: Programming Language :: Python :: 3.11
License-File: LICENSE.rst
Requires-Dist: django
